README
setup.py
uorm.py
uorm.egg-info/PKG-INFO
uorm.egg-info/SOURCES.txt
uorm.egg-info/dependency_links.txt
uorm.egg-info/requires.txt
uorm.egg-info/top_level.txt