Metadata-Version: 1.0
Name: uorm
Version: 0.2.2
Summary: Very lightweight, memory-efficient (uses generator
